Metadata-Version: 1.1
Name: django-mongodbforms
Version: 0.3.1
Summary: An implementation of django forms using mongoengine.
Home-page: http://www.schafproductions.com/projects/django-mongodb-forms/
Author: Daniel Valverde
Author-email: danielfvalverde@gmail.com
License: New BSD License
Platform: UNKNOWN
Classifier: Development Status :: 3 - Alpha
Classifier: Environment :: Web Environment
Classifier: Intended Audience :: Developers
Classifier: License :: OSI Approved :: BSD License
Classifier: Operating System :: OS Independent
Classifier: Programming Language :: Python
Classifier: Framework :: Django
